blackfynn/__init__.py
blackfynn/base.py
blackfynn/client.py
blackfynn/config.py
blackfynn/extensions.py
blackfynn/log.py
blackfynn/models.py
blackfynn/utils.py
blackfynn/api/__init__.py
blackfynn/api/agent.py
blackfynn/api/base.py
blackfynn/api/concepts.py
blackfynn/api/core.py
blackfynn/api/data.py
blackfynn/api/timeseries.py
blackfynn/api/transfers.py
blackfynn/api/user.py
blackfynn/cache/__init__.py
blackfynn/cache/cache.py
blackfynn/cache/cache_segment_pb2.py
blackfynn/cli/__init__.py
blackfynn/cli/bf_profile.py
tests/__init__.py
tests/conftest.py
tests/test_basic.py
tests/test_concepts.py
tests/test_io.py
tests/test_linked.py
tests/test_logging.py
tests/test_models.py
tests/test_templates.py
tests/test_timeseries.py
tests/utils.py
tests/resources/__init__.py
blackfynn-5.0.2.dist-info/LICENSE
blackfynn-5.0.2.dist-info/METADATA
blackfynn-5.0.2.dist-info/WHEEL
blackfynn-5.0.2.dist-info/entry_points.txt
blackfynn-5.0.2.dist-info/top_level.txt
blackfynn-5.0.2.dist-info/RECORD
