Metadata-Version: 2.1
Name: blackfynn
Version: 5.0.2
Summary: Python client for the Blackfynn Platform
Home-page: https://github.com/Blackfynn/blackfynn-python
Author: Blackfynn, Inc.
Author-email: mark@blackfynn.com
License: UNKNOWN
Project-URL: Blackfynn, https://www.blackfynn.com
Project-URL: Documentation, https://developer.blackfynn.io/python
Project-URL: Bug Reports, https://github.com/Blackfynn/blackfynn-python/issues
Keywords: blackfynn client rest api
Platform: UNKNOWN
Classifier: Development Status :: 3 - Alpha
Classifier: Topic :: Utilities
Classifier: Programming Language :: Python :: 2.7
Classifier: Programming Language :: Python :: 3.5
Classifier: Programming Language :: Python :: 3.6
Classifier: Programming Language :: Python :: 3.7
Classifier: Programming Language :: Python :: 3.8
Requires-Python: >=2.7, !=3.0.*, !=3.1.*, !=3.2.*, !=3.3.*, <4.0
Requires-Dist: pytz (>=2016)
Requires-Dist: requests (>=2.18)
Requires-Dist: protobuf (>=3.2.0)
Requires-Dist: configparser (>=3.5)
Requires-Dist: future (>=0.15.0)
Requires-Dist: futures
Requires-Dist: deprecated (>=1.2.0)
Requires-Dist: semver (>=2.8.0)
Requires-Dist: websocket-client (>=0.50.0)
Requires-Dist: docopt (>=0.6)
Requires-Dist: psutil (>=5.4)
Requires-Dist: python-dateutil (>=2.8.0)
Provides-Extra: data
Requires-Dist: numpy (>=1.13) ; extra == 'data'
Requires-Dist: pandas (>=0.20) ; extra == 'data'
